bsb_arbor/__init__.py
bsb_arbor/adapter.py
bsb_arbor/cell.py
bsb_arbor/connection.py
bsb_arbor/device.py
bsb_arbor/simulation.py
bsb_arbor/devices/__init__.py
bsb_arbor/devices/poisson_generator.py
bsb_arbor/devices/probe.py
bsb_arbor/devices/spike_recorder.py
bsb_arbor-7.2.1.dist-info/entry_points.txt
bsb_arbor-7.2.1.dist-info/licenses/LICENSE
bsb_arbor-7.2.1.dist-info/WHEEL
bsb_arbor-7.2.1.dist-info/METADATA
bsb_arbor-7.2.1.dist-info/RECORD
